lorempixel/__init__.py
lorempixel/lorem_pixel.py
python_lorem_pixel-1.0.0.dist-info/DESCRIPTION.rst
python_lorem_pixel-1.0.0.dist-info/entry_points.txt
python_lorem_pixel-1.0.0.dist-info/METADATA
python_lorem_pixel-1.0.0.dist-info/metadata.json
python_lorem_pixel-1.0.0.dist-info/pbr.json
python_lorem_pixel-1.0.0.dist-info/RECORD
python_lorem_pixel-1.0.0.dist-info/top_level.txt
python_lorem_pixel-1.0.0.dist-info/WHEEL
